{
  "period": {
    "report_date": "2026-06-22",
    "kind": "Mon",
    "cover_start": "2026-06-18",
    "cover_end": "2026-06-21",
    "slug": "2026-06-22",
    "label": "Jun 18 \u2013 Jun 21, 2026",
    "title": "Market Note \u2014 week of June 22, 2026"
  },
  "signal": {
    "btc": {
      "value": 63952.11,
      "as_of": "2026-06-22"
    },
    "mstr": {
      "value": 109.46,
      "as_of": "2026-06-22"
    },
    "mri": {
      "value": 16.22,
      "as_of": "2026-06-22"
    },
    "slope_5d": {
      "value": -2.7896,
      "as_of": "2026-06-22"
    },
    "mnav": {
      "value": 0.785,
      "as_of": "2026-06-22"
    },
    "trajectory": [
      {
        "d": "2026-05-14",
        "btc": 81051.25,
        "mstr": 186.97,
        "mri": 37.07,
        "slope": -2.4467,
        "mnav": 1.081,
        "in_window": false
      },
      {
        "d": "2026-05-15",
        "btc": 79065.68,
        "mstr": 177.42,
        "mri": 34.26,
        "slope": -2.4423,
        "mnav": 1.0516,
        "in_window": false
      },
      {
        "d": "2026-05-16",
        "btc": 78131.44,
        "mstr": null,
        "mri": 32.96,
        "slope": null,
        "mnav": 1.0641,
        "in_window": false
      },
      {
        "d": "2026-05-17",
        "btc": 77429.35,
        "mstr": null,
        "mri": 32.21,
        "slope": null,
        "mnav": 1.0738,
        "in_window": false
      },
      {
        "d": "2026-05-18",
        "btc": 76954.17,
        "mstr": 166.63,
        "mri": 31.0,
        "slope": -2.4909,
        "mnav": 0.9859,
        "in_window": false
      },
      {
        "d": "2026-05-19",
        "btc": 76750.91,
        "mstr": 164.63,
        "mri": 30.91,
        "slope": -2.4593,
        "mnav": 0.9767,
        "in_window": false
      },
      {
        "d": "2026-05-20",
        "btc": 77457.77,
        "mstr": 165.81,
        "mri": 31.77,
        "slope": -2.4666,
        "mnav": 0.9747,
        "in_window": false
      },
      {
        "d": "2026-05-21",
        "btc": 77539.17,
        "mstr": 164.85,
        "mri": 32.18,
        "slope": -2.485,
        "mnav": 0.968,
        "in_window": false
      },
      {
        "d": "2026-05-22",
        "btc": 75488.24,
        "mstr": 159.89,
        "mri": 29.69,
        "slope": -2.5109,
        "mnav": 0.9644,
        "in_window": false
      },
      {
        "d": "2026-05-23",
        "btc": 76673.37,
        "mstr": null,
        "mri": 30.86,
        "slope": null,
        "mnav": 0.9495,
        "in_window": false
      },
      {
        "d": "2026-05-24",
        "btc": 76981.12,
        "mstr": null,
        "mri": 30.89,
        "slope": null,
        "mnav": 0.9457,
        "in_window": false
      },
      {
        "d": "2026-05-25",
        "btc": 77279.93,
        "mstr": null,
        "mri": 31.78,
        "slope": null,
        "mnav": 0.942,
        "in_window": false
      },
      {
        "d": "2026-05-26",
        "btc": 75825.73,
        "mstr": 159.93,
        "mri": 29.73,
        "slope": -2.5403,
        "mnav": 0.9603,
        "in_window": false
      },
      {
        "d": "2026-05-27",
        "btc": 74344.7,
        "mstr": 154.2,
        "mri": 27.68,
        "slope": -2.6424,
        "mnav": 0.9444,
        "in_window": false
      },
      {
        "d": "2026-05-28",
        "btc": 73536.55,
        "mstr": 151.64,
        "mri": 26.73,
        "slope": -2.7148,
        "mnav": 0.9389,
        "in_window": false
      },
      {
        "d": "2026-05-29",
        "btc": 73372.52,
        "mstr": 159.09,
        "mri": 26.76,
        "slope": -2.786,
        "mnav": 0.9872,
        "in_window": false
      },
      {
        "d": "2026-05-30",
        "btc": 73754.84,
        "mstr": null,
        "mri": 27.32,
        "slope": null,
        "mnav": 0.9821,
        "in_window": false
      },
      {
        "d": "2026-05-31",
        "btc": 73579.69,
        "mstr": null,
        "mri": 27.37,
        "slope": null,
        "mnav": 0.9845,
        "in_window": false
      },
      {
        "d": "2026-06-01",
        "btc": 71319.77,
        "mstr": 149.78,
        "mri": 24.56,
        "slope": -2.8397,
        "mnav": 0.9527,
        "in_window": false
      },
      {
        "d": "2026-06-02",
        "btc": 66703.66,
        "mstr": 136.08,
        "mri": 18.27,
        "slope": -2.8436,
        "mnav": 0.9255,
        "in_window": false
      },
      {
        "d": "2026-06-03",
        "btc": 64014.37,
        "mstr": 126.55,
        "mri": 15.72,
        "slope": -2.8571,
        "mnav": 0.8968,
        "in_window": false
      },
      {
        "d": "2026-06-04",
        "btc": 63801.57,
        "mstr": 129.37,
        "mri": 14.2,
        "slope": -2.8397,
        "mnav": 0.9199,
        "in_window": false
      },
      {
        "d": "2026-06-05",
        "btc": 60922.67,
        "mstr": 120.44,
        "mri": 12.37,
        "slope": -2.8096,
        "mnav": 0.8969,
        "in_window": false
      },
      {
        "d": "2026-06-06",
        "btc": 60867.41,
        "mstr": null,
        "mri": 11.72,
        "slope": null,
        "mnav": 0.8977,
        "in_window": false
      },
      {
        "d": "2026-06-07",
        "btc": 63239.52,
        "mstr": null,
        "mri": 14.23,
        "slope": null,
        "mnav": 0.864,
        "in_window": false
      },
      {
        "d": "2026-06-08",
        "btc": 63090.59,
        "mstr": 127.2,
        "mri": 14.53,
        "slope": -2.7704,
        "mnav": 0.9164,
        "in_window": false
      },
      {
        "d": "2026-06-09",
        "btc": 61643.78,
        "mstr": 117.02,
        "mri": 12.84,
        "slope": -2.7467,
        "mnav": 0.8628,
        "in_window": false
      },
      {
        "d": "2026-06-10",
        "btc": 61449.29,
        "mstr": 115.35,
        "mri": 12.58,
        "slope": -2.7702,
        "mnav": 0.8532,
        "in_window": false
      },
      {
        "d": "2026-06-11",
        "btc": 63561.05,
        "mstr": 120.15,
        "mri": 14.83,
        "slope": -2.7586,
        "mnav": 0.8592,
        "in_window": false
      },
      {
        "d": "2026-06-12",
        "btc": 63543.2,
        "mstr": 123.97,
        "mri": 15.18,
        "slope": -2.8013,
        "mnav": 0.8867,
        "in_window": false
      },
      {
        "d": "2026-06-13",
        "btc": 64421.32,
        "mstr": null,
        "mri": 16.44,
        "slope": null,
        "mnav": 0.8746,
        "in_window": false
      },
      {
        "d": "2026-06-14",
        "btc": 65710.4,
        "mstr": null,
        "mri": 17.66,
        "slope": null,
        "mnav": 0.8575,
        "in_window": false
      },
      {
        "d": "2026-06-15",
        "btc": 66289.5,
        "mstr": 131.14,
        "mri": 18.83,
        "slope": -2.8009,
        "mnav": 0.9018,
        "in_window": false
      },
      {
        "d": "2026-06-16",
        "btc": 65600.64,
        "mstr": 122.81,
        "mri": 18.0,
        "slope": -2.805,
        "mnav": 0.8534,
        "in_window": false
      },
      {
        "d": "2026-06-17",
        "btc": 64418.45,
        "mstr": 116.56,
        "mri": 16.7,
        "slope": -2.7593,
        "mnav": 0.8249,
        "in_window": false
      },
      {
        "d": "2026-06-18",
        "btc": 62896.47,
        "mstr": 112.53,
        "mri": 14.83,
        "slope": -2.7902,
        "mnav": 0.8156,
        "in_window": true
      },
      {
        "d": "2026-06-19",
        "btc": 63540.84,
        "mstr": null,
        "mri": 15.22,
        "slope": null,
        "mnav": 0.8073,
        "in_window": true
      },
      {
        "d": "2026-06-20",
        "btc": 64239.68,
        "mstr": null,
        "mri": 16.81,
        "slope": null,
        "mnav": 0.7986,
        "in_window": true
      },
      {
        "d": "2026-06-21",
        "btc": 63237.54,
        "mstr": null,
        "mri": 15.61,
        "slope": null,
        "mnav": 0.8112,
        "in_window": true
      },
      {
        "d": "2026-06-22",
        "btc": 63952.11,
        "mstr": 109.46,
        "mri": 16.22,
        "slope": -2.7896,
        "mnav": 0.785,
        "in_window": false
      }
    ],
    "derived": {
      "mri_zone": "accumulation zone",
      "hedge_gate_open": true,
      "trend_label": "downtrend \u2014 defensive positioning permitted",
      "mnav_label": "deep discount (~0.79\u00d7 \u2014 stock below the value of the Bitcoin it holds)",
      "qfire_zone": false,
      "mri_window_dir": "lifting off the lows"
    }
  },
  "signal_plain": {
    "paragraph": "Bitcoin near $63,952, MicroStrategy near $109. The medium-term trend that governs our hedge is firmly negative, so the long-term regime is bearish and defensive positions (shorts / puts) are permitted \u2014 we are past 'watch for a top' and into an open hedge. The on-chain mean-reversion gauge is well above its capitulation extreme \u2014 no dip-buy signal, on-chain stress is not yet oversold. MicroStrategy trades at a deep discount (~0.79\u00d7 \u2014 stock below the value of the Bitcoin it holds) \u2014 a behavioural regime change (below 1.0\u00d7 the company's own policy inverts toward buying back stock rather than issuing it for Bitcoin).",
    "posture": "DEFENSIVE \u2014 bearish trend, hedge open, no buy signal yet.",
    "focus_side": "TOP"
  },
  "report": {
    "system_state": "DEFENSIVE \u2014 long-term regime bearish, hedge open (medium-term trend firmly negative), on-chain mean-reversion gauge well above its capitulation extreme (no dip-buy signal), MSTR at a deep ~0.79x discount to its Bitcoin holdings. BTC ~$63,952, MSTR ~$109. Side most needing confirmation this period: TOP.",
    "regime": "BEAR",
    "focus_side": "TOP",
    "analysts": [
      {
        "name": "James Check",
        "published": true,
        "side": "TOP",
        "lean": "confirms",
        "stance_change": true,
        "conviction": 3,
        "summary": "On Strategy's preferred stock STRC breaking below its $100 par 'overnight,' he frames it as possibly 'the market sending a more damning signal' and says it 'only works towards cementing' a few allocation decisions he has made in recent weeks regarding his Strategy-related assets. The teaser doesn't spell out the direction of those decisions, but the framing is clearly risk-OFF and lands on his good side. His top record is thin/mixed, so size it as a meaningful-but-not-decisive defensive confirmation, not gospel.",
        "quote": "the market sending a more damning signal... this event only works towards cementing",
        "url": "https://newsletter.checkonchain.com/p/saylors-sticky-situation"
      },
      {
        "name": "Lyn Alden",
        "published": true,
        "side": "NEUTRAL",
        "lean": "neutral",
        "stance_change": false,
        "conviction": 1,
        "summary": "Her post is geopolitics \u2014 the US/Iran MOU peace talks breaking down, with Iran's negotiators walking out, which she flags as keeping 'up some inflationary pressures and remain an ongoing political headache.' No stance change on BTC/MSTR, no liquidity-pivot call. Our best all-rounder, but here she gives macro color, not a same-week top or bottom trigger. Low weight; the inflation-headache lean is mildly risk-off but indirect.",
        "quote": "keep up some inflationary pressures and remain an ongoing political headache",
        "url": "https://www.lynalden.com/premium-2026-6-21/"
      },
      {
        "name": "Michael Howell",
        "published": true,
        "side": "TOP",
        "lean": "confirms",
        "stance_change": false,
        "conviction": 2,
        "summary": "Warsh's first FOMC removed the easing bias; Howell reads the new chair as 'more Volcker Red than Greenspan/Bernanke Pink' and says his US Liquidity Index 'has already been falling for several months,' so 'the peak in liquidity stimulus is behind us.' Direction is clearly risk-off and lines up with the bearish regime. But this is a restatement of an existing liquidity-down view, and he is weak on timing (often months early), so treat as directional confirmation, not a fresh trigger.",
        "quote": "the peak in liquidity stimulus is behind us",
        "url": "https://capitalwars.substack.com/p/a-new-fed-chair-the-names-bond"
      },
      {
        "name": "The Bitcoin Layer",
        "published": true,
        "side": "NEUTRAL",
        "lean": "neutral",
        "stance_change": false,
        "conviction": 1,
        "summary": "Two posts. They walk through 'TBL Liquidity's unconfirmed green dot' \u2014 the buy signal has NOT confirmed \u2014 describe a 'brutal FOMC' and a 'liquidation event in STRC,' and note a stronger dollar correlating with weaker BTC/SPX. As our one bottom-caller, the relevant read is that their dip-buy dot is explicitly unconfirmed AND the broader trend is a confirmed downtrend, where their bottom edge fails anyway. So no buy-side conviction added; if anything the unconfirmed dot and dollar strength quietly support staying defensive.",
        "quote": "TBL Liquidity's unconfirmed green dot",
        "url": "https://thebitcoinlayer.substack.com/p/when-does-the-next-green-dot-confirm"
      },
      {
        "name": "Macro Ops",
        "published": true,
        "side": "TOP",
        "lean": "confirms",
        "stance_change": true,
        "conviction": 2,
        "summary": "They acted on a 'structural shift in the Dollar's multi-month range,' confirmed an 'upside breakout' this week, and adjusted 'the Macro Ops Portfolio positioning to reflect the move,' expecting 'significant volatility.' A dollar breakout is risk-off for BTC/MSTR and it's a named-indicator turn they put real positioning behind \u2014 their good side. Per profile their defensive calls arrive late confirming a move already underway, which fits a hedge that's already open: useful corroboration, not an early warning.",
        "quote": "anticipated an upside breakout... adjust the Macro Ops Portfolio positioning",
        "url": "https://research.macro-ops.com/p/stories-we-assume-as-truth"
      },
      {
        "name": "Willy Woo",
        "published": false,
        "side": "NA",
        "lean": "silent",
        "stance_change": false,
        "conviction": 0,
        "summary": "No posts in window. A structural bull going quiet carries no information per the silence rule \u2014 note and move on.",
        "quote": "",
        "url": ""
      }
    ],
    "bear_overlay": {
      "verdict": "CORROBORATE",
      "strength": 3,
      "note": "Strong TOP-side confluence on the voices' good sides. James Check flags the STRC break as a possible 'damning signal' that cements recent Strategy-allocation decisions \u2014 a risk-OFF read from our best on-chain voice. Macro Ops put fresh positioning behind a confirmed dollar breakout. Howell's liquidity tide is falling, peak stimulus behind us. Three independent risk-off reads (on-chain, tactical, liquidity) all point the same way as the open hedge. Discount Howell/Lyn for timing and restatement, but direction is unanimous."
    },
    "qfire": {
      "verdict": "SILENT",
      "strength": 0,
      "note": "No buy-side support. The on-chain mean-reversion gauge is well above its oversold extreme, so this is NOT a capitulation \u2014 the contrarian-at-extreme 'fear is the bottom' rule does NOT apply here. The only voice that could add real buy conviction, The Bitcoin Layer, explicitly has an UNCONFIRMED green dot and the trend is a confirmed downtrend where their bottom edge fails. No dip-buy signal, no human corroboration for one. Correctly silent."
    },
    "conviction_delta": "MORE",
    "bottom_line": "MORE conviction in the DEFENSIVE posture. Three trusted voices independently confirm risk-off on their good sides, the lone bottom-caller's buy signal is unconfirmed in a broken trend, and the capitulation gauge isn't oversold \u2014 nothing argues for buying weakness yet. Watch STRC holding or losing $100 par, the dollar breakout's follow-through, and whether The Bitcoin Layer's green dot confirms (it would only matter if the trend stops breaking down).",
    "narrative_md": "**Where the system stands**\n\nThe dashboard is defensive and not subtle about it. Bitcoin sits near $63,952 and MicroStrategy near $109. The medium-term trend that governs our hedge is firmly negative, so the long-term regime reads bearish and defensive positions are open \u2014 we're past watching for a top and into a live hedge. The on-chain mean-reversion gauge is still well above its capitulation extreme, so there's no dip-buy signal; on-chain stress is not oversold. MSTR trades at roughly 0.79x the Bitcoin it holds \u2014 a deep discount that flips the company's own playbook from issuing stock toward buying it back. The question this period: do the voices we trust confirm the defensive read? They mostly do.\n\n**What the trusted voices actually said**\n\n- **James Check** \u2014 On Strategy's preferred STRC breaking below its $100 par overnight, he calls it the market possibly \"sending a more damning signal\" and says the event \"only works towards cementing\" a few decisions he's made in recent weeks on his Strategy-related allocations. The teaser doesn't say which way those decisions cut, but the framing is plainly risk-off, from our richest on-chain voice, on his good side. His top record is thin and mixed, so meaningful confirmation \u2014 not gospel. Real weight.\n- **Michael Howell** \u2014 Reads Warsh's first FOMC as removing the easing bias, calls the new chair \"more Volcker Red than Greenspan/Bernanke Pink,\" and notes his liquidity index has been falling for months: \"the peak in liquidity stimulus is behind us.\" Right direction, lines up with the regime \u2014 but a restatement, and he's weak on timing. Directional, not a trigger.\n- **Macro Ops** \u2014 Acted on a dollar breakout this week and adjusted \"the Macro Ops Portfolio positioning,\" bracing for \"significant volatility.\" A named-indicator turn with real money behind it, on their good side. Their defensive calls run late, confirming a move underway \u2014 which fits a hedge that's already open. Useful corroboration.\n- **The Bitcoin Layer** \u2014 Our one bottom-caller, and they explicitly flag an \"unconfirmed green dot.\" A brutal FOMC, an STRC liquidation, a stronger dollar dragging risk lower. The buy signal has not fired, and in a confirmed downtrend their bottom edge fails anyway. No buy conviction added.\n- **Lyn Alden** \u2014 Geopolitics: the US/Iran MOU collapsed mid-draft, Iran's negotiators walked. She sees \"ongoing political headache\" and sticky inflation. No stance change on BTC/MSTR, no liquidity pivot. Color, not a trigger.\n\n**Do the voices confirm the system?**\n\nOn the top side, yes \u2014 and cleanly. Check (on-chain), Macro Ops (tactical), and Howell (liquidity) point risk-off from three independent angles, all aligned with the open hedge. Discount Howell and Lyn for timing and restatement, but the direction is unanimous. On the buy side there's nothing: TBL's dip-buy dot is unconfirmed in a broken trend, and the capitulation gauge isn't oversold \u2014 so the \"expert fear is the bottom\" rule does not apply here. This isn't a capitulation; it's a confirmed downtrend with no oversold tell.\n\n**Bottom line**\n\nMORE conviction in the defensive posture. Watch STRC holding or losing $100, the dollar breakout's follow-through, and whether TBL's green dot confirms \u2014 though that only matters once the trend stops breaking.\n\n*Coverage note: Willy Woo was silent this window.*",
    "_generated_at": "2026-06-25 14:42 CT"
  }
}